{
	"$schema": "http://schema.management.azure.com/schemas/2015-01-01/deploymentTemplate.json#",
	"contentVersion": "1.0.0.0",
	"parameters": {
		"factoryName": {
			"type": "string",
			"metadata": "Data Factory name",
			"defaultValue": "yenuganti123"
		},
		"AzureDataLakeStorage1_accountKey": {
			"type": "secureString",
			"metadata": "Secure string for 'accountKey' of 'AzureDataLakeStorage1'"
		},
		"AzureDataLakeStorage2_accountKey": {
			"type": "secureString",
			"metadata": "Secure string for 'accountKey' of 'AzureDataLakeStorage2'"
		},
		"AzureDataLakeStorage3_accountKey": {
			"type": "secureString",
			"metadata": "Secure string for 'accountKey' of 'AzureDataLakeStorage3'"
		},
		"AzureDataLakeStorage4_accountKey": {
			"type": "secureString",
			"metadata": "Secure string for 'accountKey' of 'AzureDataLakeStorage4'"
		},
		"AzureDataLakeStorage5_accountKey": {
			"type": "secureString",
			"metadata": "Secure string for 'accountKey' of 'AzureDataLakeStorage5'"
		},
		"AzureDataLakeStorage6_accountKey": {
			"type": "secureString",
			"metadata": "Secure string for 'accountKey' of 'AzureDataLakeStorage6'"
		},
		"AzureDataLakeStorage7_accountKey": {
			"type": "secureString",
			"metadata": "Secure string for 'accountKey' of 'AzureDataLakeStorage7'"
		},
		"AzureDataLakeStorage8_accountKey": {
			"type": "secureString",
			"metadata": "Secure string for 'accountKey' of 'AzureDataLakeStorage8'"
		},
		"AzureSqlDatabase1_password": {
			"type": "secureString",
			"metadata": "Secure string for 'password' of 'AzureSqlDatabase1'"
		},
		"AzureSqlDatabase2_password": {
			"type": "secureString",
			"metadata": "Secure string for 'password' of 'AzureSqlDatabase2'"
		},
		"linkedService1_connectionString": {
			"type": "secureString",
			"metadata": "Secure string for 'connectionString' of 'linkedService1'"
		},
		"AzureDataLakeStorage1_properties_typeProperties_url": {
			"type": "string",
			"defaultValue": "https://amaras12326.dfs.core.windows.net/"
		},
		"AzureDataLakeStorage2_properties_typeProperties_url": {
			"type": "string",
			"defaultValue": "https://amaras12326.dfs.core.windows.net/"
		},
		"AzureDataLakeStorage3_properties_typeProperties_url": {
			"type": "string",
			"defaultValue": "https://amaras12326.dfs.core.windows.net/"
		},
		"AzureDataLakeStorage4_properties_typeProperties_url": {
			"type": "string",
			"defaultValue": "https://amaras12326.dfs.core.windows.net/"
		},
		"AzureDataLakeStorage5_properties_typeProperties_url": {
			"type": "string",
			"defaultValue": "https://amaras12326.dfs.core.windows.net/"
		},
		"AzureDataLakeStorage6_properties_typeProperties_url": {
			"type": "string",
			"defaultValue": "https://amaras12326.dfs.core.windows.net/"
		},
		"AzureDataLakeStorage7_properties_typeProperties_url": {
			"type": "string",
			"defaultValue": "https://amaras12326.dfs.core.windows.net/"
		},
		"AzureDataLakeStorage8_properties_typeProperties_url": {
			"type": "string",
			"defaultValue": "https://amaras12326.dfs.core.windows.net/"
		},
		"AzureSqlDatabase1_properties_typeProperties_server": {
			"type": "string",
			"defaultValue": "demobrowsejobs1234.database.windows.net"
		},
		"AzureSqlDatabase1_properties_typeProperties_database": {
			"type": "string",
			"defaultValue": "master"
		},
		"AzureSqlDatabase1_properties_typeProperties_userName": {
			"type": "string",
			"defaultValue": "admin19126"
		},
		"AzureSqlDatabase2_properties_typeProperties_server": {
			"type": "string",
			"defaultValue": "demobrowsejobs1234.database.windows.net"
		},
		"AzureSqlDatabase2_properties_typeProperties_database": {
			"type": "string",
			"defaultValue": "sunilrohitj234"
		},
		"AzureSqlDatabase2_properties_typeProperties_userName": {
			"type": "string",
			"defaultValue": "admin19126"
		}
	},
	"variables": {
		"factoryId": "[concat('Microsoft.DataFactory/factories/', parameters('factoryName'))]"
	},
	"resources": [
		{
			"name": "[concat(parameters('factoryName'), '/AzureDataLakeStorage1')]",
			"type": "Microsoft.DataFactory/factories/linkedServices",
			"apiVersion": "2018-06-01",
			"properties": {
				"annotations": [],
				"type": "AzureBlobFS",
				"typeProperties": {
					"url": "[parameters('AzureDataLakeStorage1_properties_typeProperties_url')]",
					"accountKey": {
						"type": "SecureString",
						"value": "[parameters('AzureDataLakeStorage1_accountKey')]"
					}
				}
			},
			"dependsOn": []
		},
		{
			"name": "[concat(parameters('factoryName'), '/AzureDataLakeStorage2')]",
			"type": "Microsoft.DataFactory/factories/linkedServices",
			"apiVersion": "2018-06-01",
			"properties": {
				"annotations": [],
				"type": "AzureBlobFS",
				"typeProperties": {
					"url": "[parameters('AzureDataLakeStorage2_properties_typeProperties_url')]",
					"accountKey": {
						"type": "SecureString",
						"value": "[parameters('AzureDataLakeStorage2_accountKey')]"
					}
				}
			},
			"dependsOn": []
		},
		{
			"name": "[concat(parameters('factoryName'), '/AzureDataLakeStorage3')]",
			"type": "Microsoft.DataFactory/factories/linkedServices",
			"apiVersion": "2018-06-01",
			"properties": {
				"annotations": [],
				"type": "AzureBlobFS",
				"typeProperties": {
					"url": "[parameters('AzureDataLakeStorage3_properties_typeProperties_url')]",
					"accountKey": {
						"type": "SecureString",
						"value": "[parameters('AzureDataLakeStorage3_accountKey')]"
					}
				}
			},
			"dependsOn": []
		},
		{
			"name": "[concat(parameters('factoryName'), '/AzureDataLakeStorage4')]",
			"type": "Microsoft.DataFactory/factories/linkedServices",
			"apiVersion": "2018-06-01",
			"properties": {
				"annotations": [],
				"type": "AzureBlobFS",
				"typeProperties": {
					"url": "[parameters('AzureDataLakeStorage4_properties_typeProperties_url')]",
					"accountKey": {
						"type": "SecureString",
						"value": "[parameters('AzureDataLakeStorage4_accountKey')]"
					}
				}
			},
			"dependsOn": []
		},
		{
			"name": "[concat(parameters('factoryName'), '/AzureDataLakeStorage5')]",
			"type": "Microsoft.DataFactory/factories/linkedServices",
			"apiVersion": "2018-06-01",
			"properties": {
				"annotations": [],
				"type": "AzureBlobFS",
				"typeProperties": {
					"url": "[parameters('AzureDataLakeStorage5_properties_typeProperties_url')]",
					"accountKey": {
						"type": "SecureString",
						"value": "[parameters('AzureDataLakeStorage5_accountKey')]"
					}
				}
			},
			"dependsOn": []
		},
		{
			"name": "[concat(parameters('factoryName'), '/AzureDataLakeStorage6')]",
			"type": "Microsoft.DataFactory/factories/linkedServices",
			"apiVersion": "2018-06-01",
			"properties": {
				"annotations": [],
				"type": "AzureBlobFS",
				"typeProperties": {
					"url": "[parameters('AzureDataLakeStorage6_properties_typeProperties_url')]",
					"accountKey": {
						"type": "SecureString",
						"value": "[parameters('AzureDataLakeStorage6_accountKey')]"
					}
				}
			},
			"dependsOn": []
		},
		{
			"name": "[concat(parameters('factoryName'), '/AzureDataLakeStorage7')]",
			"type": "Microsoft.DataFactory/factories/linkedServices",
			"apiVersion": "2018-06-01",
			"properties": {
				"annotations": [],
				"type": "AzureBlobFS",
				"typeProperties": {
					"url": "[parameters('AzureDataLakeStorage7_properties_typeProperties_url')]",
					"accountKey": {
						"type": "SecureString",
						"value": "[parameters('AzureDataLakeStorage7_accountKey')]"
					}
				}
			},
			"dependsOn": []
		},
		{
			"name": "[concat(parameters('factoryName'), '/AzureDataLakeStorage8')]",
			"type": "Microsoft.DataFactory/factories/linkedServices",
			"apiVersion": "2018-06-01",
			"properties": {
				"annotations": [],
				"type": "AzureBlobFS",
				"typeProperties": {
					"url": "[parameters('AzureDataLakeStorage8_properties_typeProperties_url')]",
					"accountKey": {
						"type": "SecureString",
						"value": "[parameters('AzureDataLakeStorage8_accountKey')]"
					}
				}
			},
			"dependsOn": []
		},
		{
			"name": "[concat(parameters('factoryName'), '/AzureSqlDatabase1')]",
			"type": "Microsoft.DataFactory/factories/linkedServices",
			"apiVersion": "2018-06-01",
			"properties": {
				"annotations": [],
				"type": "AzureSqlDatabase",
				"typeProperties": {
					"server": "[parameters('AzureSqlDatabase1_properties_typeProperties_server')]",
					"database": "[parameters('AzureSqlDatabase1_properties_typeProperties_database')]",
					"encrypt": "mandatory",
					"trustServerCertificate": false,
					"authenticationType": "SQL",
					"userName": "[parameters('AzureSqlDatabase1_properties_typeProperties_userName')]",
					"password": {
						"type": "SecureString",
						"value": "[parameters('AzureSqlDatabase1_password')]"
					}
				}
			},
			"dependsOn": []
		},
		{
			"name": "[concat(parameters('factoryName'), '/AzureSqlDatabase2')]",
			"type": "Microsoft.DataFactory/factories/linkedServices",
			"apiVersion": "2018-06-01",
			"properties": {
				"annotations": [],
				"type": "AzureSqlDatabase",
				"typeProperties": {
					"server": "[parameters('AzureSqlDatabase2_properties_typeProperties_server')]",
					"database": "[parameters('AzureSqlDatabase2_properties_typeProperties_database')]",
					"encrypt": "mandatory",
					"trustServerCertificate": false,
					"authenticationType": "SQL",
					"userName": "[parameters('AzureSqlDatabase2_properties_typeProperties_userName')]",
					"password": {
						"type": "SecureString",
						"value": "[parameters('AzureSqlDatabase2_password')]"
					}
				}
			},
			"dependsOn": []
		},
		{
			"name": "[concat(parameters('factoryName'), '/linkedService1')]",
			"type": "Microsoft.DataFactory/factories/linkedServices",
			"apiVersion": "2018-06-01",
			"properties": {
				"annotations": [],
				"type": "AzureBlobStorage",
				"typeProperties": {
					"connectionString": "[parameters('linkedService1_connectionString')]"
				}
			},
			"dependsOn": []
		},
		{
			"name": "[concat(parameters('factoryName'), '/Binary1')]",
			"type": "Microsoft.DataFactory/factories/datasets",
			"apiVersion": "2018-06-01",
			"properties": {
				"linkedServiceName": {
					"referenceName": "AzureDataLakeStorage4",
					"type": "LinkedServiceReference"
				},
				"annotations": [],
				"type": "Binary",
				"typeProperties": {
					"location": {
						"type": "AzureBlobFSLocation",
						"fileName": "students_practice_dataset.csv",
						"fileSystem": "venuganti123456"
					}
				}
			},
			"dependsOn": [
				"[concat(variables('factoryId'), '/linkedServices/AzureDataLakeStorage4')]"
			]
		},
		{
			"name": "[concat(parameters('factoryName'), '/Binary2')]",
			"type": "Microsoft.DataFactory/factories/datasets",
			"apiVersion": "2018-06-01",
			"properties": {
				"linkedServiceName": {
					"referenceName": "AzureDataLakeStorage1",
					"type": "LinkedServiceReference"
				},
				"annotations": [],
				"type": "Binary",
				"typeProperties": {
					"location": {
						"type": "AzureBlobFSLocation",
						"fileName": "students_practice_dataset.json",
						"fileSystem": "venuganti123456"
					}
				}
			},
			"dependsOn": [
				"[concat(variables('factoryId'), '/linkedServices/AzureDataLakeStorage1')]"
			]
		},
		{
			"name": "[concat(parameters('factoryName'), '/Binary3')]",
			"type": "Microsoft.DataFactory/factories/datasets",
			"apiVersion": "2018-06-01",
			"properties": {
				"linkedServiceName": {
					"referenceName": "AzureDataLakeStorage1",
					"type": "LinkedServiceReference"
				},
				"annotations": [],
				"type": "Binary",
				"typeProperties": {
					"location": {
						"type": "AzureBlobFSLocation",
						"fileName": "sales_practice_dataset.csv",
						"fileSystem": "venuganti123456"
					}
				}
			},
			"dependsOn": [
				"[concat(variables('factoryId'), '/linkedServices/AzureDataLakeStorage1')]"
			]
		},
		{
			"name": "[concat(parameters('factoryName'), '/DelimitedText1')]",
			"type": "Microsoft.DataFactory/factories/datasets",
			"apiVersion": "2018-06-01",
			"properties": {
				"linkedServiceName": {
					"referenceName": "AzureDataLakeStorage1",
					"type": "LinkedServiceReference"
				},
				"annotations": [],
				"type": "DelimitedText",
				"typeProperties": {
					"location": {
						"type": "AzureBlobFSLocation",
						"fileName": "students_practice_dataset.csv",
						"fileSystem": "venuganti123456"
					},
					"columnDelimiter": ",",
					"escapeChar": "\\",
					"firstRowAsHeader": true,
					"quoteChar": "\""
				},
				"schema": [
					{
						"name": "StudentID",
						"type": "String"
					},
					{
						"name": "Name",
						"type": "String"
					},
					{
						"name": "Age",
						"type": "String"
					},
					{
						"name": "Gender",
						"type": "String"
					},
					{
						"name": "Math",
						"type": "String"
					},
					{
						"name": "Science",
						"type": "String"
					},
					{
						"name": "English",
						"type": "String"
					},
					{
						"name": "Total",
						"type": "String"
					},
					{
						"name": "Grade",
						"type": "String"
					}
				]
			},
			"dependsOn": [
				"[concat(variables('factoryId'), '/linkedServices/AzureDataLakeStorage1')]"
			]
		},
		{
			"name": "[concat(parameters('factoryName'), '/DelimitedText2')]",
			"type": "Microsoft.DataFactory/factories/datasets",
			"apiVersion": "2018-06-01",
			"properties": {
				"linkedServiceName": {
					"referenceName": "AzureDataLakeStorage1",
					"type": "LinkedServiceReference"
				},
				"annotations": [],
				"type": "DelimitedText",
				"typeProperties": {
					"location": {
						"type": "AzureBlobFSLocation",
						"fileName": "students_practice_dataset.json",
						"fileSystem": "venuganti123456"
					},
					"columnDelimiter": ",",
					"escapeChar": "\\",
					"firstRowAsHeader": true,
					"quoteChar": "\""
				},
				"schema": [
					{
						"name": "{\"StudentID\":\"1\"",
						"type": "String"
					},
					{
						"name": "\"Name\":\"Ravi\"",
						"type": "String"
					},
					{
						"name": "\"Age\":\"18\"",
						"type": "String"
					},
					{
						"name": "\"Gender\":\"M\"",
						"type": "String"
					},
					{
						"name": "\"Math\":\"85\"",
						"type": "String"
					},
					{
						"name": "\"Science\":\"78\"",
						"type": "String"
					},
					{
						"name": "\"English\":\"88\"",
						"type": "String"
					},
					{
						"name": "\"Total\":\"251\"",
						"type": "String"
					},
					{
						"name": "\"Grade\":\"A\"}",
						"type": "String"
					}
				]
			},
			"dependsOn": [
				"[concat(variables('factoryId'), '/linkedServices/AzureDataLakeStorage1')]"
			]
		},
		{
			"name": "[concat(parameters('factoryName'), '/DelimitedText3')]",
			"type": "Microsoft.DataFactory/factories/datasets",
			"apiVersion": "2018-06-01",
			"properties": {
				"linkedServiceName": {
					"referenceName": "AzureDataLakeStorage1",
					"type": "LinkedServiceReference"
				},
				"annotations": [],
				"type": "DelimitedText",
				"typeProperties": {
					"location": {
						"type": "AzureBlobFSLocation",
						"fileName": "students_practice_dataset.json",
						"fileSystem": "venuganti123456"
					},
					"columnDelimiter": ",",
					"escapeChar": "\\",
					"firstRowAsHeader": true,
					"quoteChar": "\""
				},
				"schema": [
					{
						"name": "{\"StudentID\":\"1\"",
						"type": "String"
					},
					{
						"name": "\"Name\":\"Ravi\"",
						"type": "String"
					},
					{
						"name": "\"Age\":\"18\"",
						"type": "String"
					},
					{
						"name": "\"Gender\":\"M\"",
						"type": "String"
					},
					{
						"name": "\"Math\":\"85\"",
						"type": "String"
					},
					{
						"name": "\"Science\":\"78\"",
						"type": "String"
					},
					{
						"name": "\"English\":\"88\"",
						"type": "String"
					},
					{
						"name": "\"Total\":\"251\"",
						"type": "String"
					},
					{
						"name": "\"Grade\":\"A\"}",
						"type": "String"
					}
				]
			},
			"dependsOn": [
				"[concat(variables('factoryId'), '/linkedServices/AzureDataLakeStorage1')]"
			]
		},
		{
			"name": "[concat(parameters('factoryName'), '/DelimitedText4')]",
			"type": "Microsoft.DataFactory/factories/datasets",
			"apiVersion": "2018-06-01",
			"properties": {
				"linkedServiceName": {
					"referenceName": "AzureDataLakeStorage1",
					"type": "LinkedServiceReference"
				},
				"annotations": [],
				"type": "DelimitedText",
				"typeProperties": {
					"location": {
						"type": "AzureBlobFSLocation",
						"fileSystem": "archeives1"
					},
					"columnDelimiter": ",",
					"escapeChar": "\\",
					"firstRowAsHeader": true,
					"quoteChar": "\""
				},
				"schema": []
			},
			"dependsOn": [
				"[concat(variables('factoryId'), '/linkedServices/AzureDataLakeStorage1')]"
			]
		},
		{
			"name": "[concat(parameters('factoryName'), '/DelimitedText5')]",
			"type": "Microsoft.DataFactory/factories/datasets",
			"apiVersion": "2018-06-01",
			"properties": {
				"linkedServiceName": {
					"referenceName": "AzureDataLakeStorage1",
					"type": "LinkedServiceReference"
				},
				"annotations": [],
				"type": "DelimitedText",
				"typeProperties": {
					"location": {
						"type": "AzureBlobFSLocation",
						"fileName": "sales_practice_dataset.csv",
						"fileSystem": "students-data"
					},
					"columnDelimiter": ",",
					"escapeChar": "\\",
					"firstRowAsHeader": true,
					"quoteChar": "\""
				},
				"schema": [
					{
						"name": "OrderID",
						"type": "String"
					},
					{
						"name": "CustomerName",
						"type": "String"
					},
					{
						"name": "City",
						"type": "String"
					},
					{
						"name": "Product",
						"type": "String"
					},
					{
						"name": "Quantity",
						"type": "String"
					},
					{
						"name": "Price_per_Unit",
						"type": "String"
					},
					{
						"name": "Total_Amount",
						"type": "String"
					},
					{
						"name": "Order_Date",
						"type": "String"
					}
				]
			},
			"dependsOn": [
				"[concat(variables('factoryId'), '/linkedServices/AzureDataLakeStorage1')]"
			]
		},
		{
			"name": "[concat(parameters('factoryName'), '/DelimitedText6')]",
			"type": "Microsoft.DataFactory/factories/datasets",
			"apiVersion": "2018-06-01",
			"properties": {
				"linkedServiceName": {
					"referenceName": "AzureDataLakeStorage1",
					"type": "LinkedServiceReference"
				},
				"annotations": [],
				"type": "DelimitedText",
				"typeProperties": {
					"location": {
						"type": "AzureBlobFSLocation",
						"fileName": "sales_practice_dataset.csv",
						"fileSystem": "venuganti123456"
					},
					"columnDelimiter": ",",
					"escapeChar": "\\",
					"firstRowAsHeader": true,
					"quoteChar": "\""
				},
				"schema": [
					{
						"name": "OrderID",
						"type": "String"
					},
					{
						"name": "CustomerName",
						"type": "String"
					},
					{
						"name": "City",
						"type": "String"
					},
					{
						"name": "Product",
						"type": "String"
					},
					{
						"name": "Quantity",
						"type": "String"
					},
					{
						"name": "Price_per_Unit",
						"type": "String"
					},
					{
						"name": "Total_Amount",
						"type": "String"
					},
					{
						"name": "Order_Date",
						"type": "String"
					}
				]
			},
			"dependsOn": [
				"[concat(variables('factoryId'), '/linkedServices/AzureDataLakeStorage1')]"
			]
		}
	]
}